sumtex/__init__.py
sumtex/__main__.py
sumtex/latex.py
sumtex/requests.py
sumtex/version.py
sumtex-1.0.0.dist-info/LICENSE
sumtex-1.0.0.dist-info/METADATA
sumtex-1.0.0.dist-info/WHEEL
sumtex-1.0.0.dist-info/entry_points.txt
sumtex-1.0.0.dist-info/top_level.txt
sumtex-1.0.0.dist-info/RECORD
