Metadata-Version: 2.1
Name: sumtex
Version: 1.0.0
Summary: My package description
Author-email: Fabian Joswig <fabian.joswig@ed.ac.uk>
License: MIT
Keywords: GPT,latex,summarize
Classifier: Programming Language :: Python :: 3
Requires-Python: >=3.7
License-File: LICENSE
Requires-Dist: openai
